README.md
setup.py
mindstone/__init__.py
mindstone/connection.py
mindstone/constants.py
mindstone.egg-info/PKG-INFO
mindstone.egg-info/SOURCES.txt
mindstone.egg-info/dependency_links.txt
mindstone.egg-info/top_level.txt
mindstone/control/__init__.py
mindstone/control/controller.py
mindstone/control/memory.py
mindstone/control/network.py
mindstone/control/engines/__init__.py
mindstone/control/engines/body.py
mindstone/control/engines/engine.py
mindstone/control/engines/knowledge.py
mindstone/control/engines/physics.py
mindstone/control/gates/__init__.py
mindstone/control/gates/communication.py
mindstone/control/gates/config.py
mindstone/control/gates/function.py
mindstone/control/gates/gate.py
mindstone/control/gates/network.py
mindstone/control/gates/root.py
mindstone/control/gates/switch.py
mindstone/embedded/__init__.py
mindstone/embedded/coordinator.py
mindstone/embedded/driver.py
mindstone/embedded/reporting.py
mindstone/embedded/channels/__init__.py
mindstone/embedded/channels/channel.py
mindstone/embedded/channels/input.py
mindstone/embedded/channels/output.py
mindstone/embedded/channels/pwm.py
mindstone/embedded/channels/raspberry.py
mindstone/embedded/channels/virtual.py
mindstone/embedded/components/__init__.py
mindstone/embedded/components/component.py
mindstone/embedded/components/data.py
mindstone/embedded/components/led.py
mindstone/embedded/components/motor.py
mindstone/embedded/components/mutable.py
mindstone/embedded/components/observable.py
mindstone/embedded/components/servo.py
mindstone/embedded/components/switch.py
mindstone/embedded/components/ultrasonic.py
mindstone/embedded/platforms/__init__.py
mindstone/embedded/platforms/platform.py
mindstone/embedded/platforms/raspberry.py
mindstone/embedded/platforms/virtual.py