Metadata-Version: 2.1
Name: mindstone
Version: 0.0.2
Summary: The mindstone package offers an easy to use framework for creating control systems.
Home-page: https://github.com/joshuasello/mindstone
Author: Joshua Sello
Author-email: joshuasello@gmail.com
License: UNKNOWN
Download-URL: https://github.com/joshuasello/mindstone/archive/0.0.2.tar.gz
Keywords: raspberrypi,micro-controller,robots
Platform: UNKNOWN
Classifier: Programming Language :: Python :: 3
Classifier: Intended Audience :: Developers
Classifier: License :: OSI Approved :: MIT License
Classifier: Operating System :: OS Independent
Requires-Python: >=3.5
